llama_index/packs/deeplake_deepmemory_retriever/__init__.py
llama_index/packs/deeplake_deepmemory_retriever/base.py
llama_index_packs_deeplake_deepmemory_retriever-0.4.1.dist-info/METADATA
llama_index_packs_deeplake_deepmemory_retriever-0.4.1.dist-info/WHEEL
llama_index_packs_deeplake_deepmemory_retriever-0.4.1.dist-info/licenses/LICENSE
llama_index_packs_deeplake_deepmemory_retriever-0.4.1.dist-info/RECORD
