Metadata-Version: 2.4
Name: llama-index-packs-deeplake-deepmemory-retriever
Version: 0.4.1
Summary: llama-index packs deeplake_deepmemory_retriever integration
Author-email: Your Name <you@example.com>
Maintainer: AdkSarsen
License-Expression: MIT
License-File: LICENSE
Keywords: deeplake,deepmemory,retriever
Requires-Python: <4.0,>=3.9
Requires-Dist: llama-index-core<0.15,>=0.13.0
Requires-Dist: llama-index-vector-stores-deeplake<0.5,>=0.4.0
